brainmaze_utils/__init__.py
brainmaze_utils/_version.py
brainmaze_utils/files.py
brainmaze_utils/signal.py
brainmaze_utils/stat.py
brainmaze_utils/types.py
brainmaze_utils/vector.py
brainmaze_utils/annotations/__init__.py
brainmaze_utils/annotations/_io.py
brainmaze_utils/annotations/_utils.py
brainmaze_utils/annotations/_formats/CyberPSG.py
brainmaze_utils/annotations/_formats/NSRR.py
brainmaze_utils/annotations/_formats/__init__.py
brainmaze_utils/annotations/_formats/_annotation_tools/XML_CVAT.py
brainmaze_utils/annotations/_formats/_annotation_tools/XML_CyberPSG.py
brainmaze_utils/annotations/_formats/_annotation_tools/__init__.py
brainmaze_utils/annotations/_formats/_annotation_tools/xml_structured_parsing/__init__.py
brainmaze_utils/annotations/_formats/_annotation_tools/xml_structured_parsing/myXML.py
brainmaze_utils-1.0.4.dist-info/licenses/LICENSE
brainmaze_utils-1.0.4.dist-info/METADATA
brainmaze_utils-1.0.4.dist-info/WHEEL
brainmaze_utils-1.0.4.dist-info/top_level.txt
brainmaze_utils-1.0.4.dist-info/RECORD
