Metadata-Version: 2.4
Name: brainmaze-utils
Version: 1.0.4
Summary: BrainMaze: Brain Electrophysiology, Behavior and Dynamics Analysis Toolbox
Author-email: Filip Mivalt <mivalt.filip@mayo.edu>
License: BSD-3-Clause
Project-URL: Homepage, https://github.com/bnelair/brainmaze_utils
Classifier: Topic :: Scientific/Engineering :: Medical Science Apps.
Classifier: Development Status :: 3 - Alpha
Classifier: Programming Language :: Python
Classifier: Programming Language :: Python :: 3
Classifier: Programming Language :: Python :: 3.9
Classifier: Programming Language :: Python :: 3.10
Classifier: Programming Language :: Python :: 3.11
Classifier: Programming Language :: Python :: 3.12
Classifier: Operating System :: OS Independent
Classifier: License :: OSI Approved :: BSD License
Classifier: Intended Audience :: Healthcare Industry
Classifier: Intended Audience :: Science/Research
Requires-Python: >=3.9.0
License-File: LICENSE
Requires-Dist: numpy
Requires-Dist: scipy
Requires-Dist: pandas
Requires-Dist: pytz
Requires-Dist: python-dateutil
Provides-Extra: test
Requires-Dist: pytest; extra == "test"
Requires-Dist: sphinx; extra == "test"
Requires-Dist: sphinx_book_theme; extra == "test"
Requires-Dist: tqdm; extra == "test"
Dynamic: license-file
